{
    "fullscreen": {
        "x-off": 0,
        "y-off": 320,
        "width": 950,
        "height": 800
    },

    "ingame": {
        "x-off": 0,
        "y-off": 325,
        "width": 950,
        "height": 365
    },

    "loading": {
        "x-off": 10,
        "y-off": 525,
        "width": 950,
        "height": 625
    },




    "top_left": {
        "x-off": 45,
        "y-off": 620,
        "width": 435,
        "height": 690
    },
    "top_right": {
        "x-off": 515,
        "y-off": 620,
        "width": 905,
        "height": 690
    },
    "bottom_left": {
        "x-off": 45,
        "y-off": 700,
        "width": 435,
        "height": 765
    },
    "bottom_right": {
        "x-off": 515,
        "y-off": 700,
        "width": 905,
        "height": 765
    }
}